how_long_ssk/__init__.py
how_long_ssk/how_long.py
how_long_ssk-0.1.3.dist-info/WHEEL
how_long_ssk-0.1.3.dist-info/METADATA
how_long_ssk-0.1.3.dist-info/RECORD
